langtags
