Metadata-Version: 1.1
Name: langtags
Version: 2017.10.1
Summary: Provides simple format and content validation for language tags based on BCP 47 and the IANA language tag registry.
Home-page: https://github.com/jsommers/langtags
Author: Joel Sommers
Author-email: jsommers@colgate.edu
License: GPL v3
Platform: any
Classifier: Programming Language :: Python :: 2.7
Classifier: Programming Language :: Python :: 3
Classifier: Operating System :: OS Independent
Classifier: Topic :: Software Development :: Libraries :: Python Modules
Classifier: Topic :: Text Processing :: Linguistic
Classifier: License :: OSI Approved :: GNU General Public License v3 (GPLv3)
